causal_falsify/__init__.py
causal_falsify/algorithms/__init__.py
causal_falsify/algorithms/abstract.py
causal_falsify/algorithms/hgic.py
causal_falsify/algorithms/mint.py
causal_falsify/algorithms/transport.py
causal_falsify/utils/__init__.py
causal_falsify/utils/cond_indep.py
causal_falsify/utils/mint.py
causal_falsify/utils/simulate_data.py
causal_falsify-0.3.0.dist-info/licenses/LICENSE
docs/source/conf.py
tests/test_cond_indep.py
tests/test_methods_on_data.py
tests/test_simulate_data.py
tests/test_transport.py
tests/test_utils_mint.py
causal_falsify-0.3.0.dist-info/METADATA
causal_falsify-0.3.0.dist-info/WHEEL
causal_falsify-0.3.0.dist-info/top_level.txt
causal_falsify-0.3.0.dist-info/RECORD
