Metadata-Version: 2.4
Name: causal-falsify
Version: 0.3.0
Summary: Algorithms to falsify unconfoundedness assumption when having access to multi-source observational data.
Author-email: Rickard Karlsson <r.k.a.karlsson@tudelft.nl>
License: MIT
Project-URL: Homepage, https://github.com/RickardKarl/causal-falsify
Requires-Python: >=3.10
License-File: LICENSE
Requires-Dist: causal-learn>=0.1.3.8
Requires-Dist: jax>=0.4.30
Requires-Dist: matplotlib>=3.9.2
Requires-Dist: numpy>=1.26.4
Requires-Dist: pandas>=2.2.2
Requires-Dist: scikit-learn>=1.5.1
Requires-Dist: scipy>=1.12.0
Requires-Dist: seaborn>=0.13
Requires-Dist: statsmodels>=0.14.2
Requires-Dist: tqdm>=4.66.5
Provides-Extra: dev
Requires-Dist: pytest>=7.0; extra == "dev"
Requires-Dist: pytest-cov>=6.2.1; extra == "dev"
Dynamic: license-file
